.gitignore
LICENSE
README.md
commond.txt
setup.py
pydomaingibfeature/__init__.py
pydomaingibfeature.egg-info/PKG-INFO
pydomaingibfeature.egg-info/SOURCES.txt
pydomaingibfeature.egg-info/dependency_links.txt
pydomaingibfeature.egg-info/requires.txt
pydomaingibfeature.egg-info/top_level.txt