Metadata-Version: 1.1
Name: pydomaingibfeature
Version: 0.1.2
Summary: Generator gibberish feature for machine learning
Home-page: https://github.com/solopointer/pydomaingibfeature
Author: huyifeng
Author-email: solopointer@qq.com
License: MIT
Keywords: pydomaingibfeature
Platform: UNKNOWN
Classifier: Environment :: Web Environment
Classifier: Intended Audience :: Developers
Classifier: Operating System :: OS Independent
Classifier: Topic :: Text Processing :: Indexing
Classifier: Topic :: Utilities
Classifier: Topic :: Internet
Classifier: Topic :: Software Development :: Libraries :: Python Modules
Classifier: Programming Language :: Python
Classifier: Programming Language :: Python :: 2
Classifier: Programming Language :: Python :: 2.6
Classifier: Programming Language :: Python :: 2.7
